Metadata-Version: 2.1
Name: python-seed
Version: 1.1.1
Summary: Create skeleton of python project
Home-page: https://github.com/developementseed/python-seed
Author: Vincent Sarago
Author-email: vincent@developmentseed.com
License: MIT
Keywords: Python Generator tox pre-commit
Platform: UNKNOWN
Classifier: Intended Audience :: Developers
Classifier: Intended Audience :: Information Technology
Classifier: Intended Audience :: Science/Research
Classifier: License :: OSI Approved :: MIT License
Classifier: Programming Language :: Python :: 3.6
Classifier: Programming Language :: Python :: 3.7
Classifier: Programming Language :: Python :: 3.8
Classifier: Programming Language :: Python :: 3.9
Provides-Extra: test
Provides-Extra: dev
License-File: LICENSE
